{
    "uid": "https://en.wikipedia.org/wiki/Ayanna_Howard",
    "name": "Ayanna Howard",
    "has_infobox": true,
    "born": " (1972-01-24) January 24, 1972 (age\u00a046)",
    "text": "",
    "links": {
        "United States": "/wiki/United_States",
        "Roboticist": "/wiki/Roboticist",
        "Georgia Institute of Technology": "/wiki/Georgia_Institute_of_Technology",
        "Georgia Institute of Technology College of Computing": "/wiki/Georgia_Institute_of_Technology_College_of_Computing",
        "The Bionic Woman": "/wiki/The_Bionic_Woman",
        "Bachelor of Science": "/wiki/Bachelor_of_Science",
        "Engineering": "/wiki/Engineering",
        "Brown University": "/wiki/Brown_University",
        "Master of Science": "/wiki/Master_of_Science",
        "Ph.D.": "/wiki/Ph.D.",
        "Electrical Engineering": "/wiki/Electrical_Engineering",
        "University of Southern California": "/wiki/University_of_Southern_California",
        "George A. Bekey": "/wiki/George_A._Bekey",
        "NASA": "/wiki/NASA",
        "Jet Propulsion Laboratory": "/wiki/Jet_Propulsion_Laboratory",
        "Human\u2013robot interaction": "/wiki/Human%E2%80%93robot_interaction",
        "Massachusetts Institute of Technology": "/wiki/Massachusetts_Institute_of_Technology",
        "Technology Review": "/wiki/Technology_Review",
        "TR35": "/wiki/TR35",
        "TIME magazine": "/wiki/TIME_magazine",
        "USA Today": "/wiki/USA_Today"
    }
}