{
    "uid": "https://en.wikipedia.org/wiki/Edith_B%C3%BClbring",
    "name": "Edith B\u00fclbring",
    "has_infobox": true,
    "born": "(1903-12-27)27 December 1903Bonn, Germany",
    "died": "5 July 1990(1990-07-05) (aged\u00a086)Oxford, England",
    "text": "",
    "links": {
        "Fellow of the Royal Society": "/wiki/Fellow_of_the_Royal_Society",
        "Smooth muscle": "/wiki/Smooth_muscle",
        "Physiology": "/wiki/Physiology",
        "Royal Society": "/wiki/Royal_Society",
        "Pharmacology": "/wiki/Pharmacology",
        "University of Oxford": "/wiki/University_of_Oxford",
        "Emeritus": "/wiki/Emeritus",
        "Lady Margaret Hall": "/wiki/Lady_Margaret_Hall",
        "Oxford": "/wiki/Oxford",
        "Bonn": "/wiki/Bonn",
        "University of Bonn": "/wiki/University_of_Bonn",
        "University of Munich": "/wiki/University_of_Munich",
        "Albert Ludwigs University of Freiburg": "/wiki/Albert_Ludwigs_University_of_Freiburg",
        "Joshua Harold Burn": "/wiki/Joshua_Harold_Burn",
        "Pharmaceutical Society of Great Britain": "/wiki/Pharmaceutical_Society_of_Great_Britain",
        "University of London": "/wiki/University_of_London",
        "The Hague": "/wiki/The_Hague",
        "Protestant": "/wiki/Protestant",
        "Atheist": "/wiki/Atheist",
        "Netherlands": "/wiki/Netherlands",
        "Histology": "/wiki/Histology",
        "Friedrich von M\u00fcller": "/wiki/Friedrich_von_M%C3%BCller",
        "Anatomical pathology": "/wiki/Anatomical_pathology",
        "Phaeochromocytoma": "/wiki/Phaeochromocytoma",
        "Virchows Archiv": "/wiki/Virchows_Archiv",
        "Nazi party": "/wiki/Nazi_party",
        "Gustav Jacob Born": "/wiki/Gustav_Jacob_Born",
        "Serotonin": "/wiki/Serotonin",
        "Peristalsis": "/wiki/Peristalsis",
        "Sucrose gap": "/wiki/Sucrose_gap",
        "Neurotransmitter": "/wiki/Neurotransmitter",
        "Acetylcholine": "/wiki/Acetylcholine",
        "Adrenaline": "/wiki/Adrenaline",
        "Catecholamine": "/wiki/Catecholamine",
        "Atherosclerosis": "/wiki/Atherosclerosis"
    }
}