{
    "uid": "https://en.wikipedia.org/wiki/Helen_Porter",
    "name": "Helen Porter",
    "has_infobox": true,
    "born": "10 November 1893Farnham, Surrey, England",
    "died": "7 December 1987(1987-12-07) (aged\u00a088)",
    "text": "",
    "links": {
        "Royal Society of London": "/wiki/Royal_Society_of_London",
        "FRSE": "/wiki/FRSE",
        "Botany": "/wiki/Botany",
        "Imperial College London": "/wiki/Imperial_College_London",
        "Chromatography": "/wiki/Chromatography",
        "Radioactive tracers": "/wiki/Radioactive_tracers",
        "Farnham": "/wiki/Farnham",
        "Bristol": "/wiki/Bristol",
        "Victorian era": "/wiki/Victorian_era",
        "World War I": "/wiki/World_War_I",
        "Yorkshire": "/wiki/Yorkshire",
        "Danube River": "/wiki/Danube_River",
        "Arthur St George Huggett": "/wiki/Arthur_St_George_Huggett",
        "Needlework": "/wiki/Needlework",
        "Clifton High School (Bristol)": "/wiki/Clifton_High_School_(Bristol)",
        "Bedford College (London)": "/wiki/Bedford_College_(London)",
        "London University": "/wiki/London_University",
        "Birkbeck College": "/wiki/Birkbeck_College",
        "Organic chemistry": "/wiki/Organic_chemistry",
        "Barbiturate": "/wiki/Barbiturate",
        "Cambridge University": "/wiki/Cambridge_University",
        "Refrigeration": "/wiki/Refrigeration",
        "Cellular respiration": "/wiki/Cellular_respiration",
        "Organic acid": "/wiki/Organic_acid",
        "Starch": "/wiki/Starch",
        "Hemicellulose": "/wiki/Hemicellulose",
        "Pectin": "/wiki/Pectin",
        "Monocotyledon": "/wiki/Monocotyledon",
        "Barley": "/wiki/Barley",
        "World War II": "/wiki/World_War_II",
        "St. Louis": "/wiki/St._Louis",
        "Carl Ferdinand Cori": "/wiki/Carl_Ferdinand_Cori",
        "Gerty Cori": "/wiki/Gerty_Cori",
        "Enzymes": "/wiki/Enzymes",
        "Glycogen": "/wiki/Glycogen",
        "Starch phosphorylase": "/wiki/Starch_phosphorylase",
        "Nuffield Foundation": "/wiki/Nuffield_Foundation",
        "Autoradiography": "/wiki/Autoradiography",
        "Fellow of the Royal Society": "/wiki/Fellow_of_the_Royal_Society",
        "Enzymology": "/wiki/Enzymology"
    }
}