{
    "uid": "https://en.wikipedia.org/wiki/Jane_Marcet",
    "name": "Jane Marcet",
    "has_infobox": false,
    "text": "",
    "links": {
        "Science education": "/wiki/Science_education",
        "Adam Smith": "/wiki/Adam_Smith",
        "Thomas Malthus": "/wiki/Thomas_Malthus",
        "David Ricardo": "/wiki/David_Ricardo",
        "Republic of Geneva": "/wiki/Republic_of_Geneva#History",
        "Latin": "/wiki/Latin",
        "William Haldimand": "/wiki/William_Haldimand",
        "Bank of England": "/wiki/Bank_of_England",
        "Joshua Reynolds": "/wiki/Joshua_Reynolds",
        "Thomas Lawrence": "/wiki/Thomas_Lawrence",
        "Alexander John Gaspard Marcet": "/wiki/Alexander_John_Gaspard_Marcet",
        "Geneva, Switzerland": "/wiki/Geneva,_Switzerland",
        "University of Edinburgh": "/wiki/University_of_Edinburgh",
        "Guy's Hospital": "/wiki/Guy%27s_Hospital",
        "Royal Society": "/wiki/Royal_Society",
        "Mary Somerville": "/wiki/Mary_Somerville",
        "Henry Hallam": "/wiki/Henry_Hallam",
        "Harriet Martineau": "/wiki/Harriet_Martineau",
        "Auguste Arthur de la Rive": "/wiki/Auguste_Arthur_de_la_Rive",
        "Maria Edgeworth": "/wiki/Maria_Edgeworth",
        "Chemistry": "/wiki/Chemistry",
        "Botany": "/wiki/Botany",
        "Humphry Davy": "/wiki/Humphry_Davy",
        "Michael Faraday": "/wiki/Michael_Faraday",
        "Alfred Marshall": "/wiki/Alfred_Marshall",
        "Joseph Schumpeter": "/wiki/Joseph_Schumpeter",
        "Niche market": "/wiki/Niche_market",
        "Piccadilly": "/wiki/Piccadilly",
        "Henry James": "/wiki/Henry_James",
        "The Turn of the Screw": "/wiki/The_Turn_of_the_Screw",
        "University of Oxford": "/wiki/University_of_Oxford",
        "United States": "/wiki/United_States",
        "Division of labour": "/wiki/Division_of_labour",
        "Pierre Pr\u00e9vost": "/wiki/Pierre_Pr%C3%A9vost",
        "Thomas Robert Malthus": "/wiki/Thomas_Robert_Malthus",
        "James Mill": "/wiki/James_Mill",
        "Willie Henderson": "/wiki/Willie_Henderson",
        "Jean-Baptiste Say": "/wiki/Jean-Baptiste_Say",
        "Millicent Fawcett": "/wiki/Millicent_Fawcett",
        "John Stuart Mill": "/wiki/John_Stuart_Mill",
        "London": "/wiki/London"
    }
}