{
    "uid": "https://en.wikipedia.org/wiki/Joanna_S._Fowler",
    "name": "Joanna Fowler",
    "has_infobox": true,
    "born": " (1942-08-09) August 9, 1942 (age\u00a076)",
    "text": "",
    "links": {
        "U.S. Department of Energy": "/wiki/U.S._Department_of_Energy",
        "Brookhaven National Laboratory": "/wiki/Brookhaven_National_Laboratory",
        "Icahn School of Medicine at Mount Sinai": "/wiki/Icahn_School_of_Medicine_at_Mount_Sinai",
        "Radiotracer": "/wiki/Radiotracer",
        "National Medal of Science": "/wiki/National_Medal_of_Science",
        "University of South Florida": "/wiki/University_of_South_Florida",
        "Ph.D.": "/wiki/Ph.D.",
        "University of Colorado of Boulder": "/wiki/University_of_Colorado_of_Boulder",
        "Postdoctoral": "/wiki/Postdoctoral",
        "University of East Anglia": "/wiki/University_of_East_Anglia",
        "Stony Brook University": "/wiki/Stony_Brook_University",
        "Nuclear medicine": "/wiki/Nuclear_medicine",
        "Genes": "/wiki/Genes",
        "Radioactive": "/wiki/Radioactive",
        "Brain": "/wiki/Brain",
        "Cancer": "/wiki/Cancer",
        "Cocaine": "/wiki/Cocaine",
        "Fluorine": "/wiki/Fluorine",
        "Glucose": "/wiki/Glucose",
        "Positron": "/wiki/Positron",
        "Positron emission tomography": "/wiki/Positron_emission_tomography",
        "Schizophrenia": "/wiki/Schizophrenia",
        "Aging": "/wiki/Aging",
        "Monoamine oxidase": "/wiki/Monoamine_oxidase",
        "Epidemiological": "/wiki/Epidemiological",
        "Nerve-cell": "/wiki/Nerve-cell",
        "National Academy of Sciences": "/wiki/National_Academy_of_Sciences"
    }
}