{
    "uid": "https://en.wikipedia.org/wiki/Lisa_Kaltenegger",
    "name": "Lisa Kaltenegger",
    "has_infobox": true,
    "born": "4 March 1977\u00a0(1977-03-04) (age\u00a041)",
    "text": "",
    "links": {
        "Kuchl": "/wiki/Kuchl",
        "Salzburg": "/wiki/Salzburg",
        "Astronomer": "/wiki/Astronomer",
        "Exoplanets": "/wiki/Exoplanets",
        "Astrobiology": "/wiki/Astrobiology",
        "Cornell University": "/wiki/Cornell_University",
        "Max Planck Institute for Astronomy": "/wiki/Max_Planck_Institute_for_Astronomy",
        "Emmy Noether": "/wiki/Emmy_Noether",
        "Harvard University": "/wiki/Harvard_University",
        "Sub auspiciis Praesidentis": "/wiki/Sub_auspiciis_Praesidentis",
        "James Webb Space Telescope": "/wiki/James_Webb_Space_Telescope",
        "Biosignatures": "/wiki/Biosignatures",
        "Avatar (2009 film)": "/wiki/Avatar_(2009_film)",
        "Gliese 581 d": "/wiki/Gliese_581_d",
        "Habitable zone": "/wiki/Habitable_zone",
        "Kepler-62e": "/wiki/Kepler-62e",
        "Kepler-62f": "/wiki/Kepler-62f",
        "Wikipedia:Manual of Style/Dates and numbers": "/wiki/Wikipedia:Manual_of_Style/Dates_and_numbers#Chronological_items",
        "Transiting Exoplanet Survey Satellite": "/wiki/Transiting_Exoplanet_Survey_Satellite",
        "Fine Guidance Sensor": "/wiki/Fine_Guidance_Sensor",
        "Wikipedia:Citation needed": "/wiki/Wikipedia:Citation_needed",
        "Carl Sagan Institute": "/wiki/Carl_Sagan_Institute",
        "7734 Kaltenegger": "/wiki/7734_Kaltenegger",
        "Heinz Maier-Leibnitz-Preis": "/wiki/Heinz_Maier-Leibnitz-Preis"
    }
}