{
    "uid": "https://en.wikipedia.org/wiki/Marie_Crous",
    "name": "Marie Crous",
    "has_infobox": false,
    "text": "",
    "links": {
        "Charlotte-Rose de Caumont La Force": "/wiki/Charlotte-Rose_de_Caumont_La_Force",
        "Decimal": "/wiki/Decimal",
        "Marie-Madeleine de Vignerot d'Aiguillon": "/wiki/Marie-Madeleine_de_Vignerot_d%27Aiguillon",
        "Duchesse d'Aiguillon": "/wiki/Duchesse_d%27Aiguillon",
        "Cardinal de Richelieu": "/wiki/Cardinal_de_Richelieu",
        "Marin Mersenne": "/wiki/Marin_Mersenne",
        "Minim (religious order)": "/wiki/Minim_(religious_order)",
        "Simon Stevin": "/wiki/Simon_Stevin",
        "Significand": "/wiki/Significand",
        "Rule of three (mathematics)": "/wiki/Rule_of_three_(mathematics)",
        "Metric system": "/wiki/Metric_system",
        "Olry Terquem": "/wiki/Olry_Terquem",
        "Catherine Goldstein": "/wiki/Catherine_Goldstein"
    }
}