{
    "uid": "https://en.wikipedia.org/wiki/Mary_Adela_Blagg",
    "name": "Mary Adela Blagg",
    "has_infobox": false,
    "text": "",
    "links": {
        "Fellow of the Royal Astronomical Society": "/wiki/Fellow_of_the_Royal_Astronomical_Society",
        "England": "/wiki/England",
        "Astronomer": "/wiki/Astronomer",
        "Cheadle, Staffordshire": "/wiki/Cheadle,_Staffordshire",
        "Solicitor": "/wiki/Solicitor",
        "Mathematic": "/wiki/Mathematic",
        "Kensington": "/wiki/Kensington",
        "Algebra": "/wiki/Algebra",
        "German language": "/wiki/German_language",
        "Girls' Friendly Society": "/wiki/Girls%27_Friendly_Society",
        "John Herschel": "/wiki/John_Herschel",
        "Planetary nomenclature": "/wiki/Planetary_nomenclature",
        "Moon": "/wiki/Moon",
        "International Association of Academies": "/wiki/International_Association_of_Academies",
        "Variable star": "/wiki/Variable_star",
        "Monthly Notices": "/wiki/Monthly_Notices",
        "Royal Astronomical Society": "/wiki/Royal_Astronomical_Society",
        "Fourier analysis": "/wiki/Fourier_analysis",
        "Bode's Law": "/wiki/Bode%27s_Law",
        "International Astronomical Union": "/wiki/International_Astronomical_Union",
        "Nomenclature": "/wiki/Nomenclature",
        "Karl M\u00fcller (astronomer)": "/wiki/Karl_M%C3%BCller_(astronomer)",
        "M\u00fcller (lunar crater)": "/wiki/M%C3%BCller_(lunar_crater)",
        "Belgium": "/wiki/Belgium",
        "World War I": "/wiki/World_War_I",
        "Blagg (crater)": "/wiki/Blagg_(crater)"
    }
}