{
    "uid": "https://en.wikipedia.org/wiki/Reihaneh_Safavi-Naini",
    "name": "Reihaneh Safavi-Naini",
    "has_infobox": true,
    "born": "Iran",
    "text": "",
    "links": {
        "Persian language": "/wiki/Persian_language",
        "University of Calgary": "/wiki/University_of_Calgary",
        "Canada": "/wiki/Canada",
        "University of Wollongong": "/wiki/University_of_Wollongong",
        "Australia": "/wiki/Australia",
        "Cryptology": "/wiki/Cryptology",
        "Information security": "/wiki/Information_security",
        "CRYPTO (conference)": "/wiki/CRYPTO_(conference)",
        "EUROCRYPT": "/wiki/EUROCRYPT",
        "ASIACRYPT": "/wiki/ASIACRYPT",
        "Electrical and Computer Engineering": "/wiki/Electrical_and_Computer_Engineering",
        "Coding theory": "/wiki/Coding_theory",
        "University of Waterloo": "/wiki/University_of_Waterloo",
        "Electrical Engineering": "/wiki/Electrical_Engineering",
        "University of Tehran": "/wiki/University_of_Tehran",
        "Information theoretic security": "/wiki/Information_theoretic_security",
        "Provable security": "/wiki/Provable_security",
        "Network security": "/wiki/Network_security",
        "Digital Rights Management": "/wiki/Digital_Rights_Management"
    }
}