{
    "uid": "https://en.wikipedia.org/wiki/Ruth_R._Benerito",
    "name": "Ruth R. Benerito",
    "has_infobox": true,
    "born": "Ruth Mary Rogan Benerito(1916-01-12)January 12, 1916New Orleans",
    "died": "October 5, 2013(2013-10-05) (aged\u00a097)",
    "text": "",
    "links": {
        "Chemist": "/wiki/Chemist",
        "Textile industry": "/wiki/Textile_industry",
        "Permanent press": "/wiki/Permanent_press",
        "Cotton": "/wiki/Cotton",
        "Patent": "/wiki/Patent",
        "New Orleans": "/wiki/New_Orleans",
        "Higher education": "/wiki/Higher_education",
        "High school": "/wiki/High_school",
        "Sophie Newcomb College": "/wiki/Sophie_Newcomb_College",
        "Southern Regional Research Center": "/wiki/Southern_Regional_Research_Center",
        "University of New Orleans": "/wiki/University_of_New_Orleans",
        "U.S. Department of Agriculture": "/wiki/U.S._Department_of_Agriculture",
        "Wrinkle-resistant fabric": "/wiki/Wrinkle-resistant_fabric",
        "Cross-link": "/wiki/Cross-link",
        "Cellulose": "/wiki/Cellulose",
        "Polymer": "/wiki/Polymer",
        "Atoms": "/wiki/Atoms",
        "Hydrogen bonds": "/wiki/Hydrogen_bonds",
        "Korean War": "/wiki/Korean_War"
    }
}