{
    "uid": "https://en.wikipedia.org/wiki/Seema_Bhatnagar",
    "name": "Seema Bhatnagar",
    "has_infobox": true,
    "born": "Seema SrivastavaLucknow",
    "text": "",
    "links": {
        "Srivastava": "/wiki/Srivastava",
        "India": "/wiki/India",
        "Scientist": "/wiki/Scientist",
        "Anticancer": "/wiki/Anticancer",
        "Drug discovery": "/wiki/Drug_discovery",
        "Synthetic chemistry": "/wiki/Synthetic_chemistry",
        "Breast cancer": "/wiki/Breast_cancer",
        "Isabella Thoburn College": "/wiki/Isabella_Thoburn_College",
        "Chaudhary Charan Singh University": "/wiki/Chaudhary_Charan_Singh_University",
        "Central Drug Research Institute": "/wiki/Central_Drug_Research_Institute",
        "Amity University, Noida": "/wiki/Amity_University,_Noida",
        "National Institute of Immunology, India": "/wiki/National_Institute_of_Immunology,_India",
        "Council of Scientific and Industrial Research": "/wiki/Council_of_Scientific_and_Industrial_Research",
        "Ranbaxy Laboratories": "/wiki/Ranbaxy_Laboratories",
        "Indian Institute of Technology Delhi": "/wiki/Indian_Institute_of_Technology_Delhi",
        "Rajiv Gandhi Centre for Biotechnology": "/wiki/Rajiv_Gandhi_Centre_for_Biotechnology",
        "Thiruvananthapuram": "/wiki/Thiruvananthapuram",
        "University of Dundee": "/wiki/University_of_Dundee",
        "Wellcome Trust": "/wiki/Wellcome_Trust",
        "Patents": "/wiki/Patents",
        "Publications": "/wiki/Publications",
        "Annals of Oncology": "/wiki/Annals_of_Oncology",
        "Lucknow": "/wiki/Lucknow",
        "Uttar Pradesh": "/wiki/Uttar_Pradesh",
        "Defence Research and Development Organisation": "/wiki/Defence_Research_and_Development_Organisation",
        "Physiotherapist": "/wiki/Physiotherapist",
        "Wikipedia:Citation needed": "/wiki/Wikipedia:Citation_needed",
        "Intellectual property in India": "/wiki/Intellectual_property_in_India",
        "Index of women scientists articles": "/wiki/Index_of_women_scientists_articles"
    }
}