{
    "uid": "https://en.wikipedia.org/wiki/Shafi_Goldwasser",
    "name": "Shafi Goldwasser",
    "has_infobox": true,
    "born": "Shafrira GoldwasserNew York City, NY, US",
    "text": "",
    "links": {
        "Hebrew language": "/wiki/Hebrew_language",
        "Americans": "/wiki/Americans",
        "Israelis": "/wiki/Israelis",
        "Turing Award": "/wiki/Turing_Award",
        "Massachusetts Institute of Technology": "/wiki/Massachusetts_Institute_of_Technology",
        "Weizmann Institute of Science": "/wiki/Weizmann_Institute_of_Science",
        "Israel": "/wiki/Israel",
        "Simons Institute for the Theory of Computing": "/wiki/Simons_Institute_for_the_Theory_of_Computing",
        "New York City": "/wiki/New_York_City",
        "Bachelor's degree": "/wiki/Bachelor%27s_degree",
        "Carnegie Mellon University": "/wiki/Carnegie_Mellon_University",
        "Master's degree": "/wiki/Master%27s_degree",
        "Doctorate": "/wiki/Doctorate",
        "University of California, Berkeley": "/wiki/University_of_California,_Berkeley",
        "Manuel Blum": "/wiki/Manuel_Blum",
        "Theory of computation": "/wiki/Theory_of_computation",
        "MIT Computer Science and Artificial Intelligence Laboratory": "/wiki/MIT_Computer_Science_and_Artificial_Intelligence_Laboratory",
        "Proof-of-stake": "/wiki/Proof-of-stake",
        "Computational complexity theory": "/wiki/Computational_complexity_theory",
        "Cryptography": "/wiki/Cryptography",
        "Computational number theory": "/wiki/Computational_number_theory",
        "Zero-knowledge proof": "/wiki/Zero-knowledge_proof",
        "Cryptographic protocol": "/wiki/Cryptographic_protocol",
        "NP (complexity)": "/wiki/NP_(complexity)",
        "Silvio Micali": "/wiki/Silvio_Micali",
        "G\u00f6del Prize": "/wiki/G%C3%B6del_Prize",
        "Theoretical computer science": "/wiki/Theoretical_computer_science",
        "ACM Grace Murray Hopper Award": "/wiki/ACM_Grace_Murray_Hopper_Award",
        "American Academy of Arts and Sciences": "/wiki/American_Academy_of_Arts_and_Sciences",
        "National Academy of Science": "/wiki/National_Academy_of_Science",
        "National Academy of Engineering": "/wiki/National_Academy_of_Engineering",
        "International Association for Cryptologic Research": "/wiki/International_Association_for_Cryptologic_Research",
        "The Franklin Institute": "/wiki/The_Franklin_Institute",
        "The Franklin Institute Awards": "/wiki/The_Franklin_Institute_Awards",
        "IEEE Emanuel R. Piore Award": "/wiki/IEEE_Emanuel_R._Piore_Award",
        "ACM Fellow": "/wiki/ACM_Fellow"
    }
}