{
    "uid": "https://en.wikipedia.org/wiki/Sherry_Gong",
    "name": "Sherry Gong",
    "has_infobox": false,
    "text": "",
    "links": {
        "Low-dimensional topology": "/wiki/Low-dimensional_topology",
        "Mathematics competition": "/wiki/Mathematics_competition",
        "University of California, Los Angeles": "/wiki/University_of_California,_Los_Angeles",
        "New York City": "/wiki/New_York_City",
        "Toronto": "/wiki/Toronto",
        "Puerto Rico": "/wiki/Puerto_Rico",
        "New Hampshire": "/wiki/New_Hampshire",
        "MIT": "/wiki/MIT",
        "Tomasz Mrowka": "/wiki/Tomasz_Mrowka",
        "Alison Miller": "/wiki/Alison_Miller",
        "International Mathematical Olympiad": "/wiki/International_Mathematical_Olympiad",
        "Colombia": "/wiki/Colombia",
        "Math 55": "/wiki/Math_55"
    }
}